bencoding/__init__.py
bencoding/decoder.py
bencoding/encoder.py
bencoding/tokens.py
bencoding-0.2.6.dist-info/DESCRIPTION.rst
bencoding-0.2.6.dist-info/METADATA
bencoding-0.2.6.dist-info/RECORD
bencoding-0.2.6.dist-info/WHEEL
bencoding-0.2.6.dist-info/metadata.json
bencoding-0.2.6.dist-info/top_level.txt
