Metadata-Version: 1.0
Name: bencoding
Version: 0.2.6
Summary: bencoding is implemented over python3.
Home-page: https://github.com/dust8/bencoding
Author: dust8
Author-email: UNKNOWN
License: MIT
Keywords: bcode bencode bencoding torrent bittorrent
Platform: UNKNOWN
